cloud/__init__.py
cloud/contextvault_shim.py
cloud/app/__init__.py
cloud/app/auth.py
cloud/app/contextvault_adapter.py
cloud/app/db.py
cloud/app/main.py
cloud/app/adapters/core_adapter.py
cloud/app/models/pydantic_schemas.py
cloud/app/models/schemas.py
cloud/app/routes/contexts.py
cloud/tests/test_contextvault_adapter.py
cloud/tests/test_end_to_end.py
tmp_test_env/Lib/site-packages/app/core/storage/__init__.py
tmp_test_env/Lib/site-packages/app/core/storage/filelog.py
tmp_test_env/Lib/site-packages/app/core/storage/indexer.py
tmp_test_env/Lib/site-packages/app/core/storage/partitioned_filelog.py
tmp_test_env/Lib/site-packages/pip/_internal/operations/build/__init__.py
tmp_test_env/Lib/site-packages/pip/_internal/operations/build/build_tracker.py
tmp_test_env/Lib/site-packages/pip/_internal/operations/build/metadata.py
tmp_test_env/Lib/site-packages/pip/_internal/operations/build/metadata_editable.py
tmp_test_env/Lib/site-packages/pip/_internal/operations/build/metadata_legacy.py
tmp_test_env/Lib/site-packages/pip/_internal/operations/build/wheel.py
tmp_test_env/Lib/site-packages/pip/_internal/operations/build/wheel_editable.py
tmp_test_env/Lib/site-packages/pip/_internal/operations/build/wheel_legacy.py
wrappers/__init__.py
wrappers/png_builder.py
wrappers/routes_wrapper.py
wrappers/tokens.py
cloudvault_lite-0.1.0.dist-info/METADATA
cloudvault_lite-0.1.0.dist-info/WHEEL
cloudvault_lite-0.1.0.dist-info/top_level.txt
cloudvault_lite-0.1.0.dist-info/RECORD
