Metadata-Version: 2.4
Name: cloudvault-lite
Version: 0.1.0
Summary: CloudVault SaaS utilities and wrapper tooling
Author-email: Your Name or Org <you@example.com>
License: MIT
Keywords: contextvault,cloudvault,wrappers,png,qr
Classifier: Programming Language :: Python :: 3
Classifier: License :: OSI Approved :: MIT License
Classifier: Operating System :: OS Independent
Requires-Python: >=3.9
Requires-Dist: contextvault>=0.1.0
Requires-Dist: fastapi>=0.70.0
Requires-Dist: uvicorn[standard]>=0.17.0
Requires-Dist: pillow>=9.0.0
Requires-Dist: qrcode>=7.0
Requires-Dist: pyzbar>=0.1.8; platform_system == "Windows" or platform_system == "Linux" or platform_system == "Darwin"
